[
    { "_id": "A101", "title": "Propulsion Assignment", "course": "RS101", "unavailableUntil": "May 6", "unavailableUntilTime": "12:00 AM" , "dueDate": "May 20", "dueDateTime": "11:59 PM", "points": "100" },
    { "_id": "A102", "title": "Combustion Analysis", "course": "RS101", "unavailableUntil": "Jun 6", "unavailableUntilTime": "12:00 AM" , "dueDate": "Jun 20", "dueDateTime": "11:59 PM", "points": "100" },
    { "_id": "A103", "title": "Nozzle Design Project", "course": "RS101", "unavailableUntil": "Jul 6", "unavailableUntilTime": "12:00 AM" , "dueDate": "Jul 20", "dueDateTime": "11:59 PM", "points": "100" },
    { "_id": "A201", "title": "Aerodynamics Quiz", "course": "RS102", "unavailableUntil": "Aug 6", "unavailableUntilTime": "12:00 AM" , "dueDate": "Aug 20", "dueDateTime": "11:59 PM", "points": "100" },
    { "_id": "A202", "title": "Flow Analysis", "course": "RS102", "unavailableUntil": "Sep 6", "unavailableUntilTime": "12:00 AM" , "dueDate": "Sep 20", "dueDateTime": "11:59 PM", "points": "100" },
    { "_id": "A203", "title": "Heating Analysis", "course": "RS102", "unavailableUntil": "Oct 6", "unavailableUntilTime": "12:00 AM" , "dueDate": "Oct 20", "dueDateTime": "11:59 PM", "points": "100" },
    { "_id": "A301", "title": "Structural Design Task", "course": "RS103", "unavailableUntil": "Nov 6", "unavailableUntilTime": "12:00 AM" , "dueDate": "Nov 20", "dueDateTime": "11:59 PM", "points": "100" },
    { "_id": "A302", "title": "Orbital Calculations", "course": "RS103", "unavailableUntil": "Dec 6", "unavailableUntilTime": "12:00 AM" , "dueDate": "Dec 20", "dueDateTime": "11:59 PM", "points": "100" },
    { "_id": "A303", "title": "Systems Engineering Exam", "course": "RS103", "unavailableUntil": "Jan 6", "unavailableUntilTime": "12:00 AM" , "dueDate": "Jan 20", "dueDateTime": "11:59 PM", "points": "100" }
  ]